BeginnerLib.py
beginnerlib-2.1.0.dist-info/METADATA
beginnerlib-2.1.0.dist-info/WHEEL
beginnerlib-2.1.0.dist-info/top_level.txt
beginnerlib-2.1.0.dist-info/RECORD
