Metadata-Version: 2.4
Name: BeginnerLib
Version: 2.1.0
Summary: Beginner-friendly library bundling common Python utilities into a single file.
Author: Robin Parksepp
Requires-Dist: pyautogui
